youtubevideocrawler-0.1.7.dist-info/licenses/LICENSE
yt_video_crawler/__init__.py
yt_video_crawler/crawler.py
yt_video_crawler/storage.py
yt_video_crawler/utils.py
youtubevideocrawler-0.1.7.dist-info/METADATA
youtubevideocrawler-0.1.7.dist-info/WHEEL
youtubevideocrawler-0.1.7.dist-info/top_level.txt
youtubevideocrawler-0.1.7.dist-info/RECORD
