Metadata-Version: 2.4
Name: YoutubeVideoCrawler
Version: 0.1.7
Summary: A Python module that crawls YouTube videos and comments based on keywords.
Author-email: "Md. Masud Mazumder" <mdmasud.csecu@gmail.com>
License: MIT
Project-URL: Homepage, https://github.com/masud70/YoutubeDataCrawler
Requires-Python: >=3.8
License-File: LICENSE
Requires-Dist: tqdm
Requires-Dist: pandas
Requires-Dist: google-api-python-client
Dynamic: license-file
